jwcrypto/__init__.py
jwcrypto/common.py
jwcrypto/jwa.py
jwcrypto/jwe.py
jwcrypto/jwk.py
jwcrypto/jws.py
jwcrypto/jwt.py
jwcrypto/tests-cookbook.py
jwcrypto/tests.py
jwcrypto-1.5.5.data/data/share/doc/jwcrypto/LICENSE
jwcrypto-1.5.5.data/data/share/doc/jwcrypto/README.md
jwcrypto-1.5.5.dist-info/LICENSE
jwcrypto-1.5.5.dist-info/METADATA
jwcrypto-1.5.5.dist-info/WHEEL
jwcrypto-1.5.5.dist-info/top_level.txt
jwcrypto-1.5.5.dist-info/RECORD
