Metadata-Version: 2.1
Name: jwcrypto
Version: 1.5.5
Summary: Implementation of JOSE Web standards
Home-page: https://github.com/latchset/jwcrypto
Maintainer: JWCrypto Project Contributors
Maintainer-email: simo@redhat.com
License: LGPLv3+
Classifier: Programming Language :: Python :: 3.8
Classifier: Programming Language :: Python :: 3.9
Classifier: Programming Language :: Python :: 3.10
Classifier: Programming Language :: Python :: 3.11
Classifier: Intended Audience :: Developers
Classifier: Topic :: Security
Classifier: Topic :: Software Development :: Libraries :: Python Modules
Requires-Python: >= 3.8
License-File: LICENSE
